kapture/__init__.py
kapture/algo/__init__.py
kapture/algo/compare.py
kapture/algo/merge_keep_ids.py
kapture/algo/merge_reconstruction.py
kapture/algo/merge_records_data.py
kapture/algo/merge_remap.py
kapture/algo/pose_operations.py
kapture/converter/__init__.py
kapture/converter/colmap/__init__.py
kapture/converter/colmap/cameras.py
kapture/converter/colmap/database.py
kapture/converter/colmap/database_extra.py
kapture/converter/colmap/export_colmap.py
kapture/converter/colmap/export_colmap_reconstruction.py
kapture/converter/colmap/export_colmap_rigs.py
kapture/converter/colmap/import_colmap.py
kapture/converter/colmap/import_colmap_database.py
kapture/converter/colmap/import_colmap_reconstruction.py
kapture/converter/colmap/import_colmap_rigs.py
kapture/converter/downloader/__init__.py
kapture/converter/downloader/archives.py
kapture/converter/downloader/download.py
kapture/converter/exif/__init__.py
kapture/converter/exif/export_exif.py
kapture/converter/exif/import_exif.py
kapture/converter/nmea/__init__.py
kapture/converter/nmea/import_nmea.py
kapture/converter/openmvg/__init__.py
kapture/converter/openmvg/export_openmvg.py
kapture/converter/openmvg/import_openmvg.py
kapture/converter/openmvg/openmvg_commons.py
kapture/converter/opensfm/__init__.py
kapture/converter/opensfm/export_opensfm.py
kapture/converter/opensfm/import_opensfm.py
kapture/converter/ros_tools/__init__.py
kapture/converter/ros_tools/import_rosbag.py
kapture/converter/ros_tools/import_utbm_sensor.py
kapture/converter/virtual_gallery/__init__.py
kapture/converter/virtual_gallery/import_virtual_gallery.py
kapture/converter/virtual_gallery/virtual_gallery_constants.py
kapture/converter/virtual_gallery/virtual_gallery_testing.py
kapture/converter/virtual_gallery/virtual_gallery_training.py
kapture/core/ImageFeatures.py
kapture/core/Kapture.py
kapture/core/Matches.py
kapture/core/Observations.py
kapture/core/Points3d.py
kapture/core/PoseTransform.py
kapture/core/Records.py
kapture/core/Rigs.py
kapture-1.1.10.dist-info/LICENSE
kapture-1.1.10.dist-info/METADATA
kapture-1.1.10.dist-info/NOTICE
kapture-1.1.10.dist-info/WHEEL
kapture-1.1.10.dist-info/top_level.txt
kapture-1.1.10.dist-info/RECORD
