Metadata-Version: 2.1
Name: kapture
Version: 1.1.10
Summary: kapture: file format for SfM
Home-page: https://github.com/naver/kapture/
Author: naverlabs
Author-email: kapture@naverlabs.com
Classifier: Programming Language :: Python :: 3
Classifier: License :: OSI Approved :: BSD License
Classifier: Operating System :: OS Independent
Requires-Python: >=3.8
License-File: LICENSE
License-File: NOTICE
Requires-Dist: numpy >=1.16
Requires-Dist: numpy-quaternion >=2019.3.18.14.33.20
Requires-Dist: numba >=0.42
Requires-Dist: matplotlib >=3.0
Requires-Dist: scipy >=1.10.1
Requires-Dist: tqdm >=4.30
Requires-Dist: Pillow >=8.1.1
Requires-Dist: piexif ==1.1.3
Requires-Dist: requests >=2.21
Requires-Dist: pyyaml >=5.1
Requires-Dist: wcmatch >=5.0
Requires-Dist: tabulate >=0.8.7
Requires-Dist: pytz >=2021.1
Requires-Dist: build >=1.0.3
Requires-Dist: dataclasses >=0.3 ; python_version < "3.7"
Provides-Extra: dev
Requires-Dist: pytest ; extra == 'dev'
